astropalmerio/__init__.py
astropalmerio/data/emission_lines.tsv
astropalmerio/data/met_cal_for_M08_method.txt
astropalmerio/galaxies/M08.py
astropalmerio/galaxies/__init__.py
astropalmerio/galaxies/extinction.py
astropalmerio/galaxies/properties.py
astropalmerio/io/__init__.py
astropalmerio/io/ascii.py
astropalmerio/io/fits.py
astropalmerio/mc/MC_var.py
astropalmerio/mc/__arithmetic_MC_var.py
astropalmerio/mc/__init__.py
astropalmerio/mc/distributions.py
astropalmerio/mc/realizations.py
astropalmerio/mc/sampling.py
astropalmerio/mc/utils.py
astropalmerio/mc/visualization.py
astropalmerio/spectra/__init__.py
astropalmerio/spectra/conversions.py
astropalmerio/spectra/emission_lines.py
astropalmerio/spectra/reduction.py
astropalmerio/spectra/utils.py
astropalmerio/spectra/visualization.py
astropalmerio-0.1.1.dist-info/LICENSE.md
astropalmerio-0.1.1.dist-info/METADATA
astropalmerio-0.1.1.dist-info/WHEEL
astropalmerio-0.1.1.dist-info/top_level.txt
astropalmerio-0.1.1.dist-info/RECORD
