Metadata-Version: 2.1
Name: astropalmerio
Version: 0.1.1
Summary: A Python package for scientific data analysis and visualization.
Home-page: https://github.com/JPalmerio/astropalmerio
Author: Jesse Palmerio
Author-email: jesse.palmerio@obspm.fr
Project-URL: Bug Tracker, https://github.com/JPalmerio/astropalmerio/issues
Classifier: Programming Language :: Python :: 3.9
Classifier: License :: OSI Approved :: GNU General Public License v3 (GPLv3)
Classifier: Operating System :: OS Independent
Classifier: Natural Language :: English
Classifier: Intended Audience :: Science/Research
Classifier: Topic :: Scientific/Engineering :: Astronomy
Classifier: Topic :: Scientific/Engineering :: Visualization
Classifier: Development Status :: 4 - Beta
Requires-Python: >=3.9
License-File: LICENSE.md
Requires-Dist: numpy (>=1.24)
Requires-Dist: scipy (>=1.10)
Requires-Dist: astropy (>=5.2)
